pdfgetx3gui/pdffunctions.py
pdfgetx3gui/pdfgetx3_gui.py
pdfgetx3gui/exampleFiles/0p4mm_capillary_018_av17_monitor.xye
pdfgetx3gui/exampleFiles/LaB6_0p4mm_011_av10_monitor.xye
pdfgetx3gui/exampleFiles/bkg_011_av10_monitor.xye
pdfgetx3gui/icon/icon.png
pdfgetx3gui-1.2.dist-info/LICENSE
pdfgetx3gui-1.2.dist-info/METADATA
pdfgetx3gui-1.2.dist-info/WHEEL
pdfgetx3gui-1.2.dist-info/entry_points.txt
pdfgetx3gui-1.2.dist-info/top_level.txt
pdfgetx3gui-1.2.dist-info/RECORD
