Metadata-Version: 2.2
Name: pdfgetx3gui
Version: 1.2
Summary: scripts for running a GUI wrapper for PDFgetX3
Author-email: "Kenneth P. Marshall" <kenneth.marshall@esrf.fr>
Maintainer-email: "Kenneth P. Marshall" <kenneth.marshall@esrf.fr>
Project-URL: repository, https://github.com/msujas/pdfgetx3_gui.git
Keywords: PDF,pdfgetx3,gui
Classifier: Development Status :: 4 - Beta
Classifier: License :: OSI Approved :: MIT License
Classifier: Programming Language :: Python :: 3.7
Classifier: Programming Language :: Python :: 3.8
Classifier: Programming Language :: Python :: 3.9
Classifier: Programming Language :: Python :: 3.10
Requires-Python: >=3.7
License-File: LICENSE
Requires-Dist: scipy
Requires-Dist: numpy
Requires-Dist: matplotlib
Requires-Dist: PyQt5
